scixtract/__init__.py
scixtract/cli.py
scixtract/config.py
scixtract/extractor.py
scixtract/knowledge.py
scixtract/models.py
scixtract/setup.py
scixtract/text_fix.py
scixtract-1.1.1.dist-info/METADATA
scixtract-1.1.1.dist-info/WHEEL
scixtract-1.1.1.dist-info/entry_points.txt
scixtract-1.1.1.dist-info/licenses/LICENSE.txt
scixtract-1.1.1.dist-info/RECORD
