Metadata-Version: 2.4
Name: scixtract
Version: 1.1.1
Summary: AI-assisted scientific PDF text extraction using local Ollama models
License: GPL-3.0-or-later
License-File: LICENSE.txt
Keywords: pdf,extraction,ai,ollama,academic,research,knowledge,indexing
Author: Reto Stamm
Author-email: reto.stamm@example.com
Maintainer: Reto Stamm
Maintainer-email: reto.stamm@example.com
Requires-Python: >=3.10
Classifier: Development Status :: 4 - Beta
Classifier: License :: OSI Approved :: GNU General Public License v3 or later (GPLv3+)
Classifier: Intended Audience :: Science/Research
Classifier: Intended Audience :: Developers
Classifier: Operating System :: OS Independent
Classifier: Programming Language :: Python :: 3
Classifier: Programming Language :: Python :: 3.10
Classifier: Programming Language :: Python :: 3.11
Classifier: Programming Language :: Python :: 3.12
Classifier: Programming Language :: Python :: 3.13
Classifier: Topic :: Scientific/Engineering
Classifier: Topic :: Text Processing
Classifier: Topic :: Software Development :: Libraries :: Python Modules
Provides-Extra: dev
Provides-Extra: test
Requires-Dist: PyMuPDF (>=1.20.0)
Requires-Dist: bandit (>=1.7.5,<2.0.0) ; extra == "dev"
Requires-Dist: bibtexparser (>=1.4.0)
Requires-Dist: black (==26.1.0) ; extra == "dev"
Requires-Dist: bump-my-version (>=0.15.0) ; extra == "dev"
Requires-Dist: flake8 (>=6.0.0,<8.0.0) ; extra == "dev"
Requires-Dist: isort (>=5.12.0,<6.0.0) ; extra == "dev"
Requires-Dist: mypy (>=1.5.0,<2.0.0) ; extra == "dev"
Requires-Dist: pdfplumber (>=0.7.0)
Requires-Dist: pre-commit (>=3.4.0,<4.0.0) ; extra == "dev"
Requires-Dist: pytest (>=7.4.0,<9.0.0) ; extra == "dev"
Requires-Dist: pytest (>=7.4.0,<9.0.0) ; extra == "test"
Requires-Dist: pytest-cov (>=4.1.0,<6.0.0) ; extra == "dev"
Requires-Dist: pytest-cov (>=4.1.0,<6.0.0) ; extra == "test"
Requires-Dist: pytest-mock (>=3.12.0,<4.0.0) ; extra == "test"
Requires-Dist: python-magic (>=0.4.0)
Requires-Dist: requests (>=2.25.0)
Requires-Dist: tomli (>=2.0.0) ; python_version < "3.11"
Requires-Dist: tox (>=4.11.0,<5.0.0) ; extra == "dev"
Requires-Dist: types-PyYAML (>=6.0.0) ; extra == "dev"
Requires-Dist: types-requests (>=2.25.0) ; extra == "dev"
Requires-Dist: unstructured (>=0.11.0,<1.0.0)
Project-URL: Bug Tracker, https://github.com/retostamm/scixtract/issues
Project-URL: Documentation, https://github.com/retostamm/scixtract#readme
Project-URL: Homepage, https://github.com/retostamm/scixtract
Project-URL: Repository, https://github.com/retostamm/scixtract
